tests/__init__.py
tests/test.py
tineye_python/__init__.py
tineye_python/tineye_python.py
tineye_python-1.0.3.dist-info/LICENSE
tineye_python-1.0.3.dist-info/METADATA
tineye_python-1.0.3.dist-info/WHEEL
tineye_python-1.0.3.dist-info/top_level.txt
tineye_python-1.0.3.dist-info/RECORD
